<?xml version="1.0" encoding="utf-8"?>
<resources>
    <string name="label_airplane_mode">Zrakoplov</string>
    <string name="label_silent_mode">Bešumno</string>
    <string name="label_reboot">Ponovno pokreni</string>
    <string name="label_shutdown">Isključi</string>
    <string name="label_alert_reboot">Dodirni za ponovno pokretanje</string>
    <string name="label_alert_recovery">TWRP Recovery</string>
    <string name="label_alert_fastboot">Fastboot</string>
    <string name="label_alert_shutdown">Dodirni za isključivanje</string>
    <string name="label_blank">Natrag</string>
</resources>
