<?xml version="1.0" encoding="utf-8"?>
<resources>
    <string name="weather_null">Tap to get weather info</string>
    <string name="date_format">EEEE,\nd MMMM</string>
    <string name="today">Danas</string>
    <string name="tomorrow">Sjutra</string>
    <string name="aqi_pure">\'AQI \'+#weather_aqilevel</string>
    <string name="aqi_good">\'AQI \'+#weather_aqilevel</string>
    <string name="aqi_moderate">\'AQI \'+#weather_aqilevel</string>
    <string name="aqi_pollution">\'AQI \'+#weather_aqilevel</string>
    <string name="aqi_unhealthy">\'AQI \'+#weather_aqilevel</string>
    <string name="aqi_dangerous">\'AQI \'+#weather_aqilevel</string>
    <string name="aqi_hazardous">\'AQI \'+#weather_aqilevel</string>
    <string name="aqi_break">\'AQI \'+#weather_aqilevel</string>
    <string name="weather_type_null">'Nema podataka'</string>
    <string name="weather_type_0">Vedro</string>
    <string name="weather_type_1">Oblačno</string>
    <string name="weather_type_2">Izmaglica</string>
    <string name="weather_type_3">Maglovito</string>
    <string name="weather_type_4">Jako nevrijeme</string>
    <string name="weather_type_5">Kišno nevrijeme</string>
    <string name="weather_type_6">Veoma jak pljusak</string>
    <string name="weather_type_7">Oluja sa grmljavinom</string>
    <string name="weather_type_8">Pljusak</string>
    <string name="weather_type_9">Jak pljusak</string>
    <string name="weather_type_10">Kiša</string>
    <string name="weather_type_11">Lagana kiša</string>
    <string name="weather_type_12">Poledica</string>
    <string name="weather_type_13">Snježna oluja</string>
    <string name="weather_type_14">Nanosi snijega</string>
    <string name="weather_type_15">Jak snijeg</string>
    <string name="weather_type_16">Snijeg</string>
    <string name="weather_type_17">Lagan snijeg</string>
    <string name="weather_type_18">Jaka pješčana oluja</string>
    <string name="weather_type_19">Pješčana oluja</string>
    <string name="weather_type_20">Lagana pješčana oluja</string>
    <string name="weather_type_21">Pješčana oluja</string>
    <string name="weather_type_22">Grad</string>
    <string name="weather_type_23">Prašina u vazduhu</string>
    <string name="weather_type_24">Izmaglica</string>
</resources>
