<?xml version="1.0" encoding="utf-8"?>
<resources>
    <string name="label_airplane_mode">Modo avião</string>
    <string name="label_silent_mode">Silencioso</string>
    <string name="label_reboot">Reiniciar</string>
    <string name="label_shutdown">Desligar</string>
    <string name="label_alert_reboot">Reiniciar</string>
    <string name="label_alert_recovery">Recovery</string>
    <string name="label_alert_fastboot">Fastboot</string>
    <string name="label_alert_shutdown">Desligar</string>
    <string name="label_blank">Voltar</string>
</resources>
